unchained/__init__.py
unchained/admin.py
unchained/base.py
unchained/context.py
unchained/errors.py
unchained/lifespan.py
unchained/meta.py
unchained/request.py
unchained/routers.py
unchained/states.py
unchained/unchained.py
unchained/app/__init__.py
unchained/app/apps.py
unchained/cli/__init__.py
unchained/cli/db.py
unchained/cli/main.py
unchained/cli/utils.py
unchained/dependencies/__init__.py
unchained/dependencies/auto.py
unchained/dependencies/custom.py
unchained/dependencies/depends.py
unchained/dependencies/header.py
unchained/dependencies/query_params.py
unchained/docs/__init__.py
unchained/docs/swagger.py
unchained/models/__init__.py
unchained/models/base.py
unchained/models/meta.py
unchained/settings/__init__.py
unchained/settings/base.py
unchained/settings/django.py
unchained/templates/swagger.html
unchained-0.1.8.dist-info/licenses/LICENSE.md
unchained-0.1.8.dist-info/METADATA
unchained-0.1.8.dist-info/WHEEL
unchained-0.1.8.dist-info/entry_points.txt
unchained-0.1.8.dist-info/top_level.txt
unchained-0.1.8.dist-info/RECORD
