Metadata-Version: 2.4
Name: unchained
Version: 0.1.8
Summary: Modern, developer-friendly and velocity oriented Python web framework based on Django.
Author-email: Paul Brochard <paul.brochard96@gmail.com>, Maxime De Pachtere <maxime.depachtere@gmail.com>
Requires-Python: >=3.11
License-File: LICENSE.md
Requires-Dist: uvicorn>=0.34.0
Requires-Dist: fast-depends>=2.4.12
Requires-Dist: django-jazzmin>=3.0.1
Requires-Dist: typer>=0.15.2
Requires-Dist: tomli>=2.2.1
Requires-Dist: pydantic>=2.6.1
Requires-Dist: pydantic-settings>=2.8.1
Requires-Dist: penta>=0.3.0
Dynamic: license-file
